smoothglue/__init__.py
smoothglue/authentication/__init__.py
smoothglue/authentication/admin.py
smoothglue/authentication/apps.py
smoothglue/authentication/auth.py
smoothglue/authentication/defaults.py
smoothglue/authentication/migrations/0001_initial.py
smoothglue/authentication/migrations/0002_organizationmember_platformorganization_and_more.py
smoothglue/authentication/migrations/0003_platformuser_organizations_and_more.py
smoothglue/authentication/migrations/0004_platformuser_user_image_and_more.py
smoothglue/authentication/migrations/0005_platformorganization_abbreviation_and_more.py
smoothglue/authentication/migrations/0006_alter_organizationcategory_data_and_more.py
smoothglue/authentication/migrations/0007_alter_organizationcategory_options.py
smoothglue/authentication/migrations/0008_alter_platformorganization_platform_users_and_more.py
smoothglue/authentication/migrations/__init__.py
smoothglue/authentication/models.py
smoothglue/authentication/permissions.py
smoothglue/authentication/schema.py
smoothglue/authentication/serializers.py
smoothglue/authentication/tests/__init__.py
smoothglue/authentication/tests/test_admin.py
smoothglue/authentication/tests/test_auth.py
smoothglue/authentication/tests/test_models.py
smoothglue/authentication/tests/test_signals.py
smoothglue/authentication/tests/test_views.py
smoothglue/authentication/urls.py
smoothglue/authentication/views.py
smoothglue/core/__init__.py
smoothglue/core/admin.py
smoothglue/core/apps.py
smoothglue/core/field_trie.py
smoothglue/core/middleware.py
smoothglue/core/models.py
smoothglue/core/scripts/__init__.py
smoothglue/core/scripts/boot_django.py
smoothglue/core/scripts/djangoshell.py
smoothglue/core/scripts/lint.py
smoothglue/core/scripts/loaddata.py
smoothglue/core/scripts/loadtests.py
smoothglue/core/scripts/makemigrations.py
smoothglue/core/scripts/migrate.py
smoothglue/core/scripts/test_settings.py
smoothglue/core/serializers/__init__.py
smoothglue/core/serializers/abstract/__init__.py
smoothglue_django_core-1.3.4.dist-info/LICENSE
smoothglue_django_core-1.3.4.dist-info/METADATA
smoothglue_django_core-1.3.4.dist-info/NOTICE
smoothglue_django_core-1.3.4.dist-info/WHEEL
smoothglue_django_core-1.3.4.dist-info/entry_points.txt
smoothglue_django_core-1.3.4.dist-info/RECORD
