Metadata-Version: 2.3
Name: smoothglue_django_core
Version: 1.3.4
Summary: Enhance your development with SmoothGlue™, providing a user-friendly gateway to interoperable microservices for effortlessly creating complex app behaviors.
License: Proprietary
Keywords: Interoperability,API Integration,Edge Computing,Application Framework,Data-Driven Development
Author: BrainGu
Author-email: smoothglue@braingu.com
Maintainer: BrainGu
Maintainer-email: info@braingu.com
Requires-Python: >=3.12,<4.0
Classifier: Development Status :: 5 - Production/Stable
Classifier: Framework :: Django :: 5.2
Classifier: Framework :: Django
Classifier: Intended Audience :: Developers
Classifier: Topic :: Software Development :: Libraries
Classifier: Topic :: Internet :: WWW/HTTP :: Dynamic Content
Classifier: Topic :: Software Development :: Libraries :: Python Modules
Classifier: Programming Language :: Python :: 3
Classifier: Programming Language :: Python :: 3.12
Classifier: Operating System :: OS Independent
Requires-Dist: Django (>=4.2.0,<6.0.0)
Requires-Dist: PyJWT (>=2.10.1,<3.0.0)
Requires-Dist: adrf (>=0.1.9,<1.0.0)
Requires-Dist: coverage[toml] (==7.10.6)
Requires-Dist: django-cors-headers (>=4.6.0,<5.0.0)
Requires-Dist: django-filter (>=25.1,<26.0)
Requires-Dist: django-json-widget (>=2.0.1,<3.0.0)
Requires-Dist: djangorestframework (>=3.15.2,<4.0.0)
Requires-Dist: drf-spectacular (>=0.28.0,<1.0.0)
Requires-Dist: pillow (>=11.1.0,<12.0.0)
Requires-Dist: pytest (>=8.4.0)
Project-URL: Homepage, https://braingu.com/solutions/smoothglue/
Project-URL: Issues, https://braingu.com/support
